{"Exif":{"Lat":0,"Long":0,"Date":"2021-04-17T06:55:17+02:00","Tags":{"BrightnessValue":4.4078125,"ColorSpace|int":"1","ComponentsConfiguration":"","CompressedBitsPerPixel":16,"Contrast|int":"0","DateTimeOriginal|time.Time":"2021-04-17T06:55:17+02:00","DateTime|time.Time":"2021-05-31T00:12:38+02:00","DigitalZoomRatio":1,"ExifIFDPointer|int":"190","ExifVersion":"0231","ExposureBiasValue|*big.Rat":"-3/10","ExposureMode|int":"1","ExposureProgram|int":"1","ExposureTime|*big.Rat":"1/160","FNumber":6.3,"FileSource":"","Flash|int":"16","FocalLength":400,"FocalLengthIn35mmFilm|int":"400","ISOSpeedRatings|int":"500","ImageDescription":"","LensModel":"100-400mm F5-6.3 DG DN OS | Contemporary 020","LightSource|int":"0","Make":"SONY","MaxApertureValue":5.310703666997027,"MeteringMode|int":"3","Model":"ILCE-7M3","PixelXDimension|int":"2000","PixelYDimension|int":"1336","ResolutionUnit|int":"2","Saturation|int":"0","SceneCaptureType|int":"0","SceneType":"","Sharpness|int":"0","Software":"ILCE-7M3 v3.10","WhiteBalance|int":"0","XResolution":350,"YResolution":350}}}
