{"Exif":{"Lat":50.58948055,"Long":8.66735,"Date":"2018-10-14T15:33:33+02:00","Tags":{"ApertureValue":2.9708536585365852,"BrightnessValue":8.175722853817922,"ColorSpace|int":"65535","ComponentsConfiguration":"","DateTimeOriginal|time.Time":"2018-10-14T15:33:33+02:00","DateTime|time.Time":"2021-05-31T00:17:10+02:00","ExifIFDPointer|int":"198","ExifVersion":"0221","ExposureBiasValue":0,"ExposureMode|int":"0","ExposureProgram|int":"2","ExposureTime|*big.Rat":"1/169","FNumber":2.8,"Flash|int":"16","FocalLength":6.6,"FocalLengthIn35mmFilm|int":"57","GPSAltitude":155.9,"GPSAltitudeRef|int":"0","GPSDestBearing":90.378318787322,"GPSDestBearingRef":"T","GPSImgDirection":90.378318787322,"GPSImgDirectionRef":"T","GPSInfoIFDPointer|int":"642","GPSLatitude":[50,35.368833,0],"GPSLatitudeRef":"N","GPSLongitude":[8,40.041,0],"GPSLongitudeRef":"E","GPSSpeed":0.1457785367062809,"GPSSpeedRef":"K","ISOSpeedRatings|int":"20","LensMake":"Apple","LensModel":"iPhone 8 Plus back dual camera 6.6mm f/2.8","Make":"Apple","MeteringMode|int":"5","Model":"iPhone 8 Plus","Orientation|int":"1","PixelXDimension|int":"1930","PixelYDimension|int":"2000","ResolutionUnit|int":"2","SceneCaptureType|int":"0","SceneType":"","SensingMethod|int":"2","ShutterSpeedValue":7.400879443019421,"Software":"12.0.1","SubSecTimeOriginal":"377","WhiteBalance|int":"0","XResolution":72,"YResolution":72}}}
